pypkgs_tk/__init__.py
pypkgs_tk/pypkgs_tk.py
pypkgs_tk-0.1.0.dist-info/LICENSE
pypkgs_tk-0.1.0.dist-info/WHEEL
pypkgs_tk-0.1.0.dist-info/METADATA
pypkgs_tk-0.1.0.dist-info/RECORD
