Metadata-Version: 2.1
Name: pypkgs-tk
Version: 0.1.0
Summary: Python toy package to practice the process of making packages
License: MIT
Author: Trevor Kinsey
Author-email: trevor_kinsey@hotmail.com
Requires-Python: >=3.8,<4.0
Classifier: License :: OSI Approved :: MIT License
Classifier: Programming Language :: Python :: 3
Classifier: Programming Language :: Python :: 3.8
Classifier: Programming Language :: Python :: 3.9
Requires-Dist: pandas (>=1.2.2,<2.0.0)
